{"data":{"markdownRemark":{"html":"<p>I've been writing XML and related code for a number of years, and unfortunately, its still not convenient. What I mean by that is that there is still a lot of work that needs to be done before XML can get used.</p>\n<p>There are some important resources that can help make it more convenient though. I was working on a PHP / Ming SWF animation yesterday when I needed to parse an XML file into an array. SimpleXML to the rescue! That helpful library made it super easy to access the data, and its awesome that something is available in Perl as well.</p>\n<p>\"Simple XML\" is nice because while we all want our data to be nice and organized, its great when it can be quickly and efficiently accessed in a script.</p>","frontmatter":{"title":"Convenient XML","date":"2008-11-29T00:00:00.000Z"}}},"pageContext":{"isCreatedByStatefulCreatePages":false,"slug":"/2008/2008-11-29-convenient-xml/"}}