{"data":{"markdownRemark":{"html":"<p>There are many different flavors of Ubuntu:</p>\n<ul><li>Ubuntu - the main distribution</li><li>Kubuntu - KDE based Ubuntu</li><li>Edubuntu - an Ubuntu tailored for education, includes a nifty LTSP server</li><li>Xubuntu - A lightweight version of Ubuntu</li><li>Fluxbuntu - an even lighter version of ubuntu</li></ul>\n<p>More!</p>\n<ul><li><a href=\"http://www.ubuntustudio.org/\">http://www.ubuntustudio.org/</a></li>","frontmatter":{"title":"buntu Guide"}}},"pageContext":{"isCreatedByStatefulCreatePages":false,"slug":"/2007/2007-07-03-buntu-guide/"}}