{"data":{"markdownRemark":{"html":"<p>Tired of waiting for Rails 3 to start up again and again, I decided to try out Ruby 1.9.3-rc1. To my surprised, Ruby 1.9.3-rc1 works reliably well!</p>\n<p>The great part about this is how much faster Rails 3 starts up when using Ruby 1.9.3. Its like night and day.</p>\n<p>I am keeping 1.9.2 installed, and thankfully its not too much of a burden since I'm using rbenv (similar to rvm).</p>\n<p>Let's go to the races!</p>\n<h4>The Simplest Race (A Rake Task)</h4>\n<pre class=\"sh_ruby\">\nnamespace :speed do\n  task :check => :environment do\n    puts \"Testing...\"\n  end\nend\n</pre>\n<h4>Ruby 1.9.2-p290</h4>\n<pre class=\"terminal\">\ntime rake speed:check\nreal    0m44.346s\nuser    0m42.215s\nsys     0m1.416s\n</pre>\n<h4>Ruby 1.9.3-rc1</h4>\n<pre class=\"terminal\">\ntime rake speed:check\nreal    0m12.646s\nuser    0m11.749s\nsys     0m0.784s\n</pre>\n<p>Awesome!!</p>","frontmatter":{"title":"Ruby 1.9.3 and Rails 3.1.1"}}},"pageContext":{"isCreatedByStatefulCreatePages":false,"slug":"/2011/2011-10-15-ruby-193-and-rails-311/"}}