{"data":{"markdownRemark":{"html":"<p>Since I switch to Movable Type, some of the web services offered here have suffered. More specifically, they've stopped working.</p>\n<p>I fixed a couple of them today, namely:</p>\n<ul><li><a href=\"http://www.docunext.com/blog/simple-dns-timer.html\">Simple DNS Timer</a></li><li><a href=\"http://www.docunext.com/blog/dig.html\">Online Dig</a></li><li><a href=\"http://www.docunext.com/blog/what-is-my-ip.html\">What is my IP?</a></li></ul>\nEnjoy!","frontmatter":{"title":"Docunext Tools Are Working Again"}}},"pageContext":{"isCreatedByStatefulCreatePages":false,"slug":"/2009/2009-08-01-docunext-tools-are-working-again/"}}